[
    {
        "id": "3e9c9c52-88ff-45de-8425-548a0cd575c8",
        "name": "Gamepad",
        "price": "40000",
        "sale_price": null,
        "on_sale": false,
        "category": "Accessories",
        "description": "Very good, Brand new",
        "stock": 7,
        "colors": [
            "Red",
            "Yellow",
            "Green",
            "Gold"
        ],
        "sizes": [
            "34",
            "56",
            "90"
        ],
        "images": [
            "pexels-garrettmorrow-682933.jpg"
        ],
        "timestamp": "2025-10-17T22:29:01.673090"
    },
    {
        "id": "3add6997-71c2-4ba5-ab00-9a23b2f84784",
        "name": "Charger",
        "price": "23",
        "sale_price": null,
        "on_sale": false,
        "category": "Accessories",
        "description": "",
        "stock": 50,
        "colors": [
            "white"
        ],
        "sizes": [],
        "images": [
            "pexels-inspiredimages-139038.jpg"
        ],
        "timestamp": "2025-10-17T22:36:19.901604"
    },
    {
        "id": "7c407031-e830-4a38-a2de-c0fc34b6c403",
        "name": "Kk",
        "price": "450",
        "sale_price": null,
        "on_sale": false,
        "featured": true,
        "category": "Accessories",
        "description": "mmm",
        "stock": 50,
        "colors": [
            "white"
        ],
        "sizes": [
            "38",
            "67"
        ],
        "images": [
            "IMG-20251002-WA0002.jpg",
            "IMG-20251002-WA0003.jpg"
        ],
        "timestamp": "2025-11-02T18:49:41.469928+00:00"
    },
    {
        "id": "f0c4134d-c5e9-445b-86cf-eda5c1bf279f",
        "name": "Kk",
        "price": "450",
        "sale_price": null,
        "on_sale": false,
        "featured": false,
        "category": "Accessories",
        "description": "mnkj",
        "stock": 50,
        "colors": [
            "white"
        ],
        "sizes": [
            "38",
            "67"
        ],
        "images": [
            "IMG-20251002-WA0004.jpg",
            "IMG-20251002-WA0005.jpg",
            "IMG-20251002-WA0006.jpg"
        ],
        "timestamp": "2025-11-02T18:52:16.105324+00:00"
    },
    {
        "id": "79be58d2-55ae-45bf-a67b-784c7ff83df8",
        "name": "Mm",
        "price": "45",
        "sale_price": null,
        "on_sale": false,
        "featured": false,
        "category": "Accessories",
        "description": "",
        "stock": 45,
        "colors": [
            "blue"
        ],
        "sizes": [
            "27",
            "28"
        ],
        "images": [
            "8b900e48-aadf-4638-8bcf-1f464f846856.jpeg"
        ],
        "timestamp": "2025-11-06T09:15:44.299731+00:00"
    },
    {
        "id": "1e777167-c966-47c5-bc3e-4163ef55e46e",
        "name": "Sneaker",
        "price": "678",
        "sale_price": null,
        "on_sale": false,
        "featured": false,
        "category": "Tops",
        "description": "",
        "stock": 23,
        "colors": [],
        "sizes": [],
        "images": [
            "batman-x-joker-symphony-d5-1920x1080.jpg"
        ],
        "timestamp": "2025-11-06T13:02:25.571171+00:00"
    }
]